README.md
setup.py
gainz/__init__.py
gainz/totalReturn.py
gainz_jwfu.egg-info/PKG-INFO
gainz_jwfu.egg-info/SOURCES.txt
gainz_jwfu.egg-info/dependency_links.txt
gainz_jwfu.egg-info/top_level.txt