Metadata-Version: 2.1
Name: gainz-jwfu
Version: 0.0.1
Summary: Calculates returns of equities available on AlphaVantage
Home-page: https://github.com/jwfu/gainz
Author: Jun Wei Fu
Author-email: pypi.solecistic@aleeas.com
License: UNKNOWN
Platform: UNKNOWN
Classifier: Programming Language :: Python :: 3
Classifier: License :: OSI Approved :: MIT License
Classifier: Operating System :: OS Independent
Requires-Python: >=3.6
